piper_whistle/__init__.py
piper_whistle/cli.py
piper_whistle/cmds.py
piper_whistle/db.py
piper_whistle/holz.py
piper_whistle/search.py
piper_whistle/util.py
piper_whistle/version.py
piper_whistle-1.6.253.dist-info/METADATA
piper_whistle-1.6.253.dist-info/WHEEL
piper_whistle-1.6.253.dist-info/entry_points.txt
piper_whistle-1.6.253.dist-info/license.md
piper_whistle-1.6.253.dist-info/top_level.txt
piper_whistle-1.6.253.dist-info/RECORD
