Metadata-Version: 2.1
Name: piper-whistle
Version: 1.6.253
Summary: CLI tool to manage piper voices.
Home-page: https://gitlab.com/think-biq/piper-whistle
Author: biq
Author-email: sven.freiberg@biq.solutions
Keywords: text-to-speech piper voice model tool
Classifier: Programming Language :: Python :: 3
Classifier: License :: OSI Approved :: MIT License
Classifier: Operating System :: OS Independent
Requires-Python: >=3.8
License-File: license.md
Requires-Dist: attrs ==23.1.0
Requires-Dist: certifi ==2023.7.22
Requires-Dist: charset-normalizer ==3.3.2
Requires-Dist: filelock ==3.13.1
Requires-Dist: fsspec ==2023.10.0
Requires-Dist: huggingface-hub ==0.18.0
Requires-Dist: idna ==3.4
Requires-Dist: mdurl ==0.1.2
Requires-Dist: PyYAML ==6.0.1
Requires-Dist: rapidfuzz ==3.5.1
Requires-Dist: requests ==2.31.0
Requires-Dist: thefuzz ==0.20.0
Requires-Dist: tqdm ==4.66.1
Requires-Dist: typing-extensions ==4.8.0
Requires-Dist: urllib3 ==2.0.7
Requires-Dist: userpaths ==0.1.3
